fw_presidio_image_redactor/__init__.py
fw_presidio_image_redactor/fw_scan_and_redact.py
fw_presidio_image_redactor/main.py
fw_presidio_image_redactor/nlp_configs/__init__.py
fw_presidio_image_redactor/nlp_configs/recognizer_config.py
fw_presidio_image_redactor/nlp_configs/transformers.yaml
fw_presidio_image_redactor/output.py
fw_presidio_image_redactor/parser.py
fw_presidio_image_redactor/utils/__init__.py
fw_presidio_image_redactor/utils/alg_progress_tracking.py
fw_presidio_image_redactor/utils/bbox_fuser.py
fw_presidio_image_redactor/utils/easy_ocr.py
fw_presidio_image_redactor/utils/pretrained_transformer.py
fw_presidio_image_redactor/utils/reader_tasks.py
fw_presidio_image_redactor/utils/schemas/annotation_schema.json
fw_presidio_image_redactor/utils/schemas/form_schema.json
fw_presidio_image_redactor/utils/schemas/reader_task.json
fw_presidio_image_redactor/utils/schemas/viewer_config_schema.json
fw_presidio_image_redactor/utils/transformer_recognizer.py
fw_presidio_image_redactor-0.1.3.dist-info/LICENSE
fw_presidio_image_redactor-0.1.3.dist-info/METADATA
fw_presidio_image_redactor-0.1.3.dist-info/WHEEL
fw_presidio_image_redactor-0.1.3.dist-info/RECORD
