Metadata-Version: 2.1
Name: fw-presidio-image-redactor
Version: 0.1.3
Summary: {{description}}
Home-page: https://gitlab.com/flywheel-io/scientific-solutions/gears/presidio-image-redactor
License: MIT
Keywords: Flywheel,Gears
Author: Flywheel
Author-email: support@flywheel.io
Requires-Python: >=3.9,<4.0
Classifier: License :: OSI Approved :: MIT License
Classifier: Programming Language :: Python :: 3
Classifier: Programming Language :: Python :: 3.9
Classifier: Programming Language :: Python :: 3.10
Classifier: Programming Language :: Python :: 3.11
Classifier: Programming Language :: Python :: 3.12
Classifier: Topic :: Scientific/Engineering
Requires-Dist: azure-ai-formrecognizer (>=3.3.1,<4.0.0)
Requires-Dist: azure-ai-ml (>=1.11.1,<2.0.0)
Requires-Dist: azure-core (>=1.29.5,<2.0.0)
Requires-Dist: easyocr (>=1.7.1,<2.0.0)
Requires-Dist: flywheel-gear-toolkit (>=0.6.11,<0.7.0)
Requires-Dist: flywheel-sdk (==16.16.7)
Requires-Dist: fw-client (>=0.8.5,<0.9.0)
Requires-Dist: fw-file (>=3.4.0,<4.0.0)
Requires-Dist: huggingface-hub (>=0.19.4,<0.20.0)
Requires-Dist: numpy (==1.26.4)
Requires-Dist: opencv-python (>=4.7.0.68,<5.0.0.0)
Requires-Dist: pandas (>=2.2.3,<3.0.0)
Requires-Dist: presidio-analyzer (>=2.2.32,<3.0.0)
Requires-Dist: presidio-anonymizer (>=2.2.32,<3.0.0)
Requires-Dist: presidio-image-redactor (>=0.0.53,<0.0.54)
Requires-Dist: pydicom (>=2.3.1,<3.0.0)
Requires-Dist: pymongo (>=4.9.1,<5.0.0)
Requires-Dist: pytest-mock (>=3.14.0,<4.0.0)
Requires-Dist: python-gdcm (>=3.0.21,<4.0.0)
Requires-Dist: ruamel-yaml (>=0.18.6,<0.19.0)
Requires-Dist: scikit-learn (>=1.5.2,<2.0.0)
Requires-Dist: spacy (>=3.7.6,<4.0.0)
Requires-Dist: spacy-huggingface-pipelines (>=0.0.4,<0.0.5)
Requires-Dist: torch (>=2.1.1,<3.0.0)
Requires-Dist: transformers (>=4.35.2,<5.0.0)
Project-URL: Repository, https://gitlab.com/flywheel-io/scientific-solutions/gears/presidio-image-redactor
